komolibs/__init__.py
komolibs/aws/__init__.py
komolibs/aws/s3/__init__.py
komolibs/aws/s3/download.py
komolibs/aws/s3/s3_base.py
komolibs/aws/s3/upload.py
komolibs/caching/__init__.py
komolibs/caching/cache_reader.py
komolibs/caching/cache_writer.py
komolibs/core/__init__.py
komolibs/core/utils/__init__.py
komolibs/core/utils/async_utils.py
komolibs/core/utils/time_formatter.py
komolibs/db/__init__.py
komolibs/db/influx/__init__.py
komolibs/db/influx/influx_data.py
komolibs/logger/__init__.py
komolibs/logger/application_warning.py
komolibs/logger/logger.py
komolibs/logger/struct_logger.py
komolibs/messaging/__init__.py
komolibs/pubsub/__init__.py
komolibs/pubsub/publish.py
komolibs/pubsub/subscribe.py
komolibs-0.1.530.dist-info/WHEEL
komolibs-0.1.530.dist-info/METADATA
komolibs-0.1.530.dist-info/RECORD
