Metadata-Version: 2.1
Name: komolibs
Version: 0.1.530
Summary: 
Author: Makhosonke Morafo
Author-email: makhosonke@komokun.org
Requires-Python: >=3.8,<4.0
Classifier: Programming Language :: Python :: 3
Classifier: Programming Language :: Python :: 3.8
Classifier: Programming Language :: Python :: 3.9
Requires-Dist: aioredis (>=1.3.1,<2.0.0)
Requires-Dist: boto3 (>=1.18.27,<2.0.0)
Requires-Dist: influxdb-client (>=1.19.0,<2.0.0)
Requires-Dist: pendulum (>=2.1.2,<3.0.0)
Requires-Dist: redis (>=3.5.3,<4.0.0)
